ManyRequests/WebRunner.py
ManyRequests/__init__.py
ManyRequests-0.0.3.dist-info/METADATA
ManyRequests-0.0.3.dist-info/RECORD
ManyRequests-0.0.3.dist-info/WHEEL
ManyRequests-0.0.3.dist-info/top_level.txt
