Metadata-Version: 2.1
Name: ManyRequests
Version: 0.0.3
Summary: A library to make many requests concurrently.
Home-page: https://github.com/kbeauregard/ManyRequests
Author: Kyle Beauregard
Author-email: kylembeauregard@gmail.com
License: UNKNOWN
Platform: UNKNOWN
Classifier: Programming Language :: Python :: 2
Classifier: Operating System :: OS Independent
Requires-Dist: requests (>=2.5.1)
